Metadata-Version: 2.4
Name: llm-tools-quickjs
Version: 0.1
Summary: JavaScript execution as a tool for LLM
Author: Simon Willison
License-Expression: Apache-2.0
Project-URL: Homepage, https://github.com/simonw/llm-tools-quickjs
Project-URL: Changelog, https://github.com/simonw/llm-tools-quickjs/releases
Project-URL: Issues, https://github.com/simonw/llm-tools-quickjs/issues
Project-URL: CI, https://github.com/simonw/llm-tools-quickjs/actions
Requires-Python: >=3.9
License-File: LICENSE
Requires-Dist: llm>=0.26
Requires-Dist: quickjs
Provides-Extra: test
Requires-Dist: pytest; extra == "test"
Requires-Dist: llm-echo>=0.3a1; extra == "test"
Dynamic: license-file
